{
    "slug": "nombre-del-plan",
    "title": "Título del Plan Alimenticio",
    "type": "Tipo de Alimentación: Ej. Balanceada",
    "duration": "Ej: 1 día / 1 semana",
    "image": "assets/images/ruta-a-la-portada-del-plan.webp",
    "introduction": "<p>Breve descripción introductoria sobre los objetivos y beneficios de este plan.</p>",
    "schedule": [
        {
            "name": "Día 1",
            "meals": [
                {
                    "type": "Desayuno",
                    "recipeIds": [
                        "id_receta_1",
                        "id_receta_2"
                    ]
                },
                {
                    "type": "Almuerzo",
                    "recipeIds": [
                        "id_receta_3"
                    ]
                },
                {
                    "type": "Snack",
                    "recipeIds": [
                        "id_receta_4"
                    ]
                },
                {
                    "type": "Cena",
                    "recipeIds": [
                        "id_receta_5"
                    ]
                }
            ]
        }
    ]
}